{
  "guides": [
    {
      "url": "https://estudiobitcoin.com/",
      "icon": "https://bushido.guide/img/favicon/favicon-EB.png",
      "lang": "esp",
      "tags": [""],
      "name": "Estudio Bitcoin",
      "description": "Es un espacio en español con todos los recursos necesarios para empezar y profundizar en Bitcoin"
    },{
      "url": "https://blockmit.com/",
      "icon": "https://blockmit.com/wp-content/uploads/2020/04/block1.png",
      "lang": "esp",
      "tags": [""],
      "name": "Blockmit",
      "description": "Creador de uno de los sistemas mas populares para la autocustodia de tus llaves privadas"
    },{
      "url": "https://www.econoalchemist.com/",
      "icon": "https://images-wixmp-7ef3383b5fd80a9f5a5cc686.wixmp.com/5f5f18ac-c971-4321-b80e-79177199dddb/1603678440900-IMG_3029.jpeg/v1/fill/w_320,h_320/file.jpg",
      "lang": "eng",
      "tags": ["privacy","custody","mining"],
      "name": "econoalchemist",
      "description": "Bitcoin, Self Custody, & Censorship Resistance"
    },{
      "url": "https://k3tan.com/",
      "icon": "https://k3tan.com/bl-themes/darktheme//img/favicon.png",
      "lang": "eng",
      "tags": ["nodes","custody"],
      "name": "K3tan",
      "description": "Bitcoin | FOSS"
    }, {
      "url": "https://diverter.hostyourown.tools/",
      "icon": "https://diverter.hostyourown.tools/content/images/size/w150/2021/07/1611626619256.jpg",
      "lang": "eng",
      "tags": ["nodes","custody"],
      "name": "Diverter",
      "description": "Focused on bitcoin, privacy, and censorship resistance. Use the tools."
    },{
      "url": "https://bitcoiner.guide/",
      "icon": "https://bitcoiner.guide/favicon.ico",
      "lang": "eng",
      "tags": ["privacy", "tools", ""],
      "name": "Bitcoiner Guide",
      "description": "A collection of its contributions that it can point people towards when starting out. If you find it valuable, please share it with your peers."
    },{
      "url": "https://bitcoin.cipix.eu/",
      "icon": "https://cdn.substack.com/image/fetch/w_96,c_limit,f_auto,q_auto:good,fl_progressive:steep/https%3A%2F%2Fbucketeer-e05bbc84-baa3-437e-9518-adb32be77984.s3.amazonaws.com%2Fpublic%2Fimages%2Fc5993420-c6c3-4610-9186-a6d102e51577_250x250.png",
      "lang": "esp",
      "tags": ["privacy", "tools", "guide"],
      "name": "Soberania Financiera",
      "description": "En primer lugar, lo siento por el diseño web de mierda, pero el objetivo de esta web no es ser elegante, y es mejor que lo veas en los navegadores de escritorio, en los móviles se ve realmente horrible, lo sé"
    },{
      "url": "https://dinerosinreglas.com/",
      "icon": "https://sp-ao.shortpixel.ai/client/to_webp,q_glossy,ret_img/https://dinerosinreglas.com/wp-content/uploads/2021/03/DecentraIcon200x200.png",
      "lang": "esp",
      "tags": ["privacy", "tools", "guide", "on-chain"],
      "name": "Dinero sin reglas",
      "description": "Es un apasionado de la tecnología y del cómo esto nos puede ayudar a ser mejores. Desde que conocio Bitcoin le ha vuelto un fan de sus conceptos, su filosofía y de toda la tecnología que emerge a su alrededor."
    }, {
      "url": "https://darthcoin.substack.com/archive",
      "icon": "https://cdn.substack.com/image/fetch/w_96,c_limit,f_auto,q_auto:good,fl_progressive:steep/https%3A%2F%2Fbucketeer-e05bbc84-baa3-437e-9518-adb32be77984.s3.amazonaws.com%2Fpublic%2Fimages%2Fc5993420-c6c3-4610-9186-a6d102e51577_250x250.png",
      "lang": "eng",
      "tags": ["cli-wallet", "on-chain"],
      "name": "Darth Coin",
      "description": "Just an old bitcoiner (toxic) maximalist, that from 2012 (when started with Bitcoin) was an unknown identity in Bitcoinlandia. But starting with 2019 decided to go out and start helping newbies and onboard more nocoiners into Bitcoin (so far 400+ new bitcoiners created in the last 2 years)."
    },{
      "url": "https://learnmeabitcoin.com/",
      "icon": "https://learnmeabitcoin.com/favicon.ico",
      "lang": "eng",
      "tags": ["bitcoin", "on-chain", "learn"],
      "name": "Learn Me Bitcoin",
      "description": "I have no official qualification in Bitcoin. I've just read a lot of code, written a lot of code, and asked a lot of questions. Everything I know about bitcoin comes from practice. Also, I am cool"
    },{
      "url": "https://preguntasbitcoin.com/",
      "icon": "https://preguntasbitcoin.com/preguntas_bitcoin/img/pb_stamp.png",
      "lang": "esp",
      "tags": ["bitcoin", "questions", "q&a"],
      "name": "Preguntas Bitcoin",
      "description": "Envíanos tu pregunta rellenando el formulario y en las próximas 24 horas tendrás respuesta de un miembro de la comunidad hispana de Bitcoin"
    },{
      "url": "https://river.com/learn/",
      "icon": "https://blog.river.com/favicon.ico",
      "lang": "eng",
      "tags": ["bitcoin", "learn"],
      "name": "River",
      "description": "Bitcoin Learning Center"
    },{
      "url": "https://braiins.com/blog",
      "icon": "https://assets.website-files.com/5e5ee6f9b325a6509259421f/5f8438dff3d08e8684d73972_II%20logo%402x-1.png",
      "lang": "eng",
      "tags": ["bitcoin", "guide", "mining"],
      "name": "Braiins",
      "description": "Read our insider takes on the Bitcoin mining industry along with deep dives into the technology and use cases for projects including Slush Pool, Braiins OS+, Stratum V2, and more"
    },{
      "url": "https://econoalchemist.github.io/",
      "icon": "https://econoalchemist.github.io/logo.png",
      "lang": "eng",
      "tags": ["bitcoin", "guide", "mining", "privacy"],
      "name": "Econoalchemist | Blog",
      "description": "The econoalchemist blog is focused on keeping Bitcoin permissionless by offering content on self custody, censorship resistance, and home mining."
    },
    {
      "url": "https://sovrnbitcoiner.com/",
      "icon": "https://sovrnbitcoiner.com/content/images/2022/08/E0DDFC88-D797-4141-8793-96B78EFF1D75-4.jpg",
      "lang": "eng",
      "tags": [],
      "name": "sovrn Bitcoiner",
      "description": "We are at war with them. They do not want us to do what we are doing and so fuck it, if its war.. lets get the battle gear on and use the tools that are available."
    },
    {
      "url": "https://bitcoin-1o1.info/",
      "icon": "https://bitcoin-1o1.info/favicon.ico",
      "lang": "esp",
      "tags": [],
      "name": "Bitcoin 1o1",
      "description": "Explicaciones simples, pero no superficiales"
    },
    {
      "url": "https://github.com/tipogi/honey-badger-land",
      "icon": "https://avatars.githubusercontent.com/u/103417381?v=4",
      "lang": "eng",
      "tags": [],
      "name": "Honey Badger Land",
      "description": "Want it to be sovereign? Install in the PC Pop!_OS and configure, installing minimal software"
    },
    {
      "url": "https://kyc3.life/",
      "icon": "https://kyc3.life/wp-content/uploads/2022/08/cropped-no-kyc-icon-32x32.jpg",
      "lang": "eng",
      "tags": ["guides", "nokyc"],
      "name": "KYC Free Life",
      "description": "Sovereignty, Privacy & Economic Freedom"
    },
    {
      "url": "https://airgapcomputer.com/",
      "icon": "none",
      "lang": "eng",
      "tags": ["guides", "wallet"],
      "name": "Warning",
      "description": "How to setup a Bitcoin Air-Gap Computer? DON'T"
    },
    {
      "url": "https://thebitcoinrabbithole.com/chapter-1-money/",
      "icon": "https://thebitcoinrabbithole.com/wp-content/uploads/2022/05/cropped-Logo-pour-site-192x192.png",
      "lang": "eng",
      "tags": ["guides", "general"],
      "name": "The bitcoin Rabbit Hole",
      "description": "After spending more than 6 years studying it, the only thing I know for sure is that Bitcoin is greater than us all"
    }
  ]
}